wmath/__init__.py
wmath/cross.py
wmath/fraction.py
wmath/matrix.py
wmath/meta.py
wmath/number_theory.py
wmath/paradigm.py
wmath/polynomial.py
wmath-0.1.0.dist-info/LICENSE
wmath-0.1.0.dist-info/METADATA
wmath-0.1.0.dist-info/WHEEL
wmath-0.1.0.dist-info/top_level.txt
wmath-0.1.0.dist-info/RECORD
