Metadata-Version: 2.1
Name: wmath
Version: 0.1.0
Summary: Another simple mathematical package in the world
Home-page: https://github.com/wang606/wmath
Author: wang606
Author-email: wang__qing__hua@163.com
License: UNKNOWN
Project-URL: Bug Tracker, https://github.com/wang606/wmath/issues
Platform: UNKNOWN
Classifier: Programming Language :: Python :: 3
Classifier: License :: OSI Approved :: MIT License
Classifier: Operating System :: OS Independent
Requires-Python: >=3.6
License-File: LICENSE
